UART_Tx.v

// This file contains the UART Transmitter.  This transmitter is able
// to transmit 8 bits of serial data, one start bit, one stop bit,
// and no parity bit.  When transmit is complete o_Tx_done will be
// driven high for one clock cycle.
//
// Set Parameter CLKS_PER_BIT as follows:
// CLKS_PER_BIT = (Frequency of i_Clock)/(Frequency of UART)
// Example: 25 MHz Clock, 115200 baud UART
// (25000000)/(115200) = 217
 
module UART_TX 
  #(parameter CLKS_PER_BIT = 217)
  (
   input       i_Rst_L,
   input       i_Clock,
   input       i_TX_DV,
   input [7:0] i_TX_Byte, 
   output reg  o_TX_Active,
   output reg  o_TX_Serial,
   output reg  o_TX_Done
   );
 
  localparam IDLE         = 2'b00;
  localparam TX_START_BIT = 2'b01;
  localparam TX_DATA_BITS = 2'b10;
  localparam TX_STOP_BIT  = 2'b11;
  
  reg [2:0] r_SM_Main;
  reg [$clog2(CLKS_PER_BIT):0] r_Clock_Count;
  reg [2:0] r_Bit_Index;
  reg [7:0] r_TX_Data;


  // Purpose: Control TX state machine
  always @(posedge i_Clock or negedge i_Rst_L)
  begin
    if (~i_Rst_L)
    begin
      r_SM_Main <= 3'b000;
    end
    else
    begin

      o_TX_Done <= 1'b0;

      case (r_SM_Main)
      IDLE :
        begin
          o_TX_Serial   <= 1'b1;         // Drive Line High for Idle
          r_Clock_Count <= 0;
          r_Bit_Index   <= 0;
          
          if (i_TX_DV == 1'b1)
          begin
            o_TX_Active <= 1'b1;
            r_TX_Data   <= i_TX_Byte;
            r_SM_Main   <= TX_START_BIT;
          end
          else
            r_SM_Main <= IDLE;
        end // case: IDLE
      
      
      // Send out Start Bit. Start bit = 0
      TX_START_BIT :
        begin
          o_TX_Serial <= 1'b0;
          
          // Wait CLKS_PER_BIT-1 clock cycles for start bit to finish
          if (r_Clock_Count < CLKS_PER_BIT-1)
          begin
            r_Clock_Count <= r_Clock_Count + 1;
            r_SM_Main     <= TX_START_BIT;
          end
          else
          begin
            r_Clock_Count <= 0;
            r_SM_Main     <= TX_DATA_BITS;
          end
        end // case: TX_START_BIT
      
      
      // Wait CLKS_PER_BIT-1 clock cycles for data bits to finish         
      TX_DATA_BITS :
        begin
          o_TX_Serial <= r_TX_Data[r_Bit_Index];
          
          if (r_Clock_Count < CLKS_PER_BIT-1)
          begin
            r_Clock_Count <= r_Clock_Count + 1;
            r_SM_Main     <= TX_DATA_BITS;
          end
          else
          begin
            r_Clock_Count <= 0;
            
            // Check if we have sent out all bits
            if (r_Bit_Index < 7)
            begin
              r_Bit_Index <= r_Bit_Index + 1;
              r_SM_Main   <= TX_DATA_BITS;
            end
            else
            begin
              r_Bit_Index <= 0;
              r_SM_Main   <= TX_STOP_BIT;
            end
          end 
        end // case: TX_DATA_BITS
      
      
      // Send out Stop bit.  Stop bit = 1
      TX_STOP_BIT :
        begin
          o_TX_Serial <= 1'b1;
          
          // Wait CLKS_PER_BIT-1 clock cycles for Stop bit to finish
          if (r_Clock_Count < CLKS_PER_BIT-1)
          begin
            r_Clock_Count <= r_Clock_Count + 1;
            r_SM_Main     <= TX_STOP_BIT;
          end
          else
          begin
            o_TX_Done     <= 1'b1;
            r_Clock_Count <= 0;
            r_SM_Main     <= IDLE;
            o_TX_Active   <= 1'b0;
          end 
        end // case: TX_STOP_BIT      
      
      default :
        r_SM_Main <= IDLE;
      
    endcase
    end // else: !if(~i_Rst_L)
  end // always @ (posedge i_Clock or negedge i_Rst_L)

  
endmodule

UART_Rx.v

// This file contains the UART Receiver.  This receiver is able to
// receive 8 bits of serial data, one start bit, one stop bit,
// and no parity bit.  When receive is complete o_rx_dv will be
// driven high for one clock cycle.
// 
// Set Parameter CLKS_PER_BIT as follows:
// CLKS_PER_BIT = (Frequency of i_Clock)/(Frequency of UART)
// Example: 25 MHz Clock, 115200 baud UART
// (25000000)/(115200) = 217
 
module UART_RX
  #(parameter CLKS_PER_BIT = 217)
  (
   input        i_Clock,
   input        i_RX_Serial,
   output       o_RX_DV,
   output [7:0] o_RX_Byte
   );
   
  parameter IDLE         = 3'b000;
  parameter RX_START_BIT = 3'b001;
  parameter RX_DATA_BITS = 3'b010;
  parameter RX_STOP_BIT  = 3'b011;
  parameter CLEANUP      = 3'b100;
  
  reg [7:0]     r_Clock_Count = 0;
  reg [2:0]     r_Bit_Index   = 0; //8 bits total
  reg [7:0]     r_RX_Byte     = 0;
  reg           r_RX_DV       = 0;
  reg [2:0]     r_SM_Main     = 0;
  
  
  // Purpose: Control RX state machine
  always @(posedge i_Clock)
  begin
      
    case (r_SM_Main)
      IDLE :
        begin
          r_RX_DV       <= 1'b0;
          r_Clock_Count <= 0;
          r_Bit_Index   <= 0;
          
          if (i_RX_Serial == 1'b0)          // Start bit detected
            r_SM_Main <= RX_START_BIT;
          else
            r_SM_Main <= IDLE;
        end
      
      // Check middle of start bit to make sure it's still low
      RX_START_BIT :
        begin
          if (r_Clock_Count == (CLKS_PER_BIT-1)/2)
          begin
            if (i_RX_Serial == 1'b0)
            begin
              r_Clock_Count <= 0;  // reset counter, found the middle
              r_SM_Main     <= RX_DATA_BITS;
            end
            else
              r_SM_Main <= IDLE;
          end
          else
          begin
            r_Clock_Count <= r_Clock_Count + 1;
            r_SM_Main     <= RX_START_BIT;
          end
        end // case: RX_START_BIT
      
      
      // Wait CLKS_PER_BIT-1 clock cycles to sample serial data
      RX_DATA_BITS :
        begin
          if (r_Clock_Count < CLKS_PER_BIT-1)
          begin
            r_Clock_Count <= r_Clock_Count + 1;
            r_SM_Main     <= RX_DATA_BITS;
          end
          else
          begin
            r_Clock_Count          <= 0;
            r_RX_Byte[r_Bit_Index] <= i_RX_Serial;
            
            // Check if we have received all bits
            if (r_Bit_Index < 7)
            begin
              r_Bit_Index <= r_Bit_Index + 1;
              r_SM_Main   <= RX_DATA_BITS;
            end
            else
            begin
              r_Bit_Index <= 0;
              r_SM_Main   <= RX_STOP_BIT;
            end
          end
        end // case: RX_DATA_BITS
      
      
      // Receive Stop bit.  Stop bit = 1
      RX_STOP_BIT :
        begin
          // Wait CLKS_PER_BIT-1 clock cycles for Stop bit to finish
          if (r_Clock_Count < CLKS_PER_BIT-1)
          begin
            r_Clock_Count <= r_Clock_Count + 1;
     	    r_SM_Main     <= RX_STOP_BIT;
          end
          else
          begin
       	    r_RX_DV       <= 1'b1;
            r_Clock_Count <= 0;
            r_SM_Main     <= CLEANUP;
          end
        end // case: RX_STOP_BIT
      
      
      // Stay here 1 clock
      CLEANUP :
        begin
          r_SM_Main <= IDLE;
          r_RX_DV   <= 1'b0;
        end
      
      
      default :
        r_SM_Main <= IDLE;
      
    endcase
  end    
  
  assign o_RX_DV   = r_RX_DV;
  assign o_RX_Byte = r_RX_Byte;
  
endmodule // UART_RX

UART_TB.v
// This testbench will exercise the UART RX.
// It sends out byte 0x37, and ensures the RX receives it correctly.
`timescale 1ns/10ps

`include "UART_TX.v"

module UART_TB ();

  // Testbench uses a 25 MHz clock
  // Want to interface to 115200 baud UART
  // 25000000 / 115200 = 217 Clocks Per Bit.
  parameter c_CLOCK_PERIOD_NS = 40;
  parameter c_CLKS_PER_BIT    = 217;
  parameter c_BIT_PERIOD      = 8600;
  
  reg r_Clock = 0;
  reg r_TX_DV = 0;
  wire w_TX_Active, w_UART_Line;
  wire w_TX_Serial;
  reg [7:0] r_TX_Byte = 0;
  wire [7:0] w_RX_Byte;

  UART_RX #(.CLKS_PER_BIT(c_CLKS_PER_BIT)) UART_RX_Inst
    (.i_Clock(r_Clock),
     .i_RX_Serial(w_UART_Line),
     .o_RX_DV(w_RX_DV),
     .o_RX_Byte(w_RX_Byte)
     );
  
  UART_TX #(.CLKS_PER_BIT(c_CLKS_PER_BIT)) UART_TX_Inst
    (.i_Clock(r_Clock),
     .i_TX_DV(r_TX_DV),
     .i_TX_Byte(r_TX_Byte),
     .o_TX_Active(w_TX_Active),
     .o_TX_Serial(w_TX_Serial),
     .o_TX_Done()
     );

  // Keeps the UART Receive input high (default) when
  // UART transmitter is not active
  assign w_UART_Line = w_TX_Active ? w_TX_Serial : 1'b1;
    
  always
    #(c_CLOCK_PERIOD_NS/2) r_Clock <= !r_Clock;
  
  // Main Testing:
  initial
    begin
      // Tell UART to send a command (exercise TX)
      @(posedge r_Clock);
      @(posedge r_Clock);
      r_TX_DV   <= 1'b1;
      r_TX_Byte <= 8'h3F;
      @(posedge r_Clock);
      r_TX_DV <= 1'b0;

      // Check that the correct command was received
      @(posedge w_RX_DV);
      if (w_RX_Byte == 8'h3F)
        $display("Test Passed - Correct Byte Received");
      else
        $display("Test Failed - Incorrect Byte Received");
      $finish();
    end
  
  initial 
  begin
    // Required to dump signals to EPWave
    $dumpfile("dump.vcd");
    $dumpvars(0);
  end
endmodule

dump.vcd
$date
	Thu Jan 04 19:08:05 2024
$end
$version
	ModelSim Version 2020.1
$end
$timescale
	10ps
$end

$scope module UART_TB $end
$var parameter 32 ! c_CLOCK_PERIOD_NS $end
$var parameter 32 " c_CLKS_PER_BIT $end
$var parameter 32 # c_BIT_PERIOD $end
$var reg 1 $ r_Clock $end
$var reg 1 % r_TX_DV $end
$var wire 1 & w_TX_Active $end
$var wire 1 ' w_UART_Line $end
$var wire 1 ( w_TX_Serial $end
$var reg 8 ) r_TX_Byte [7:0] $end
$var wire 1 * w_RX_Byte [7] $end
$var wire 1 + w_RX_Byte [6] $end
$var wire 1 , w_RX_Byte [5] $end
$var wire 1 - w_RX_Byte [4] $end
$var wire 1 . w_RX_Byte [3] $end
$var wire 1 / w_RX_Byte [2] $end
$var wire 1 0 w_RX_Byte [1] $end
$var wire 1 1 w_RX_Byte [0] $end
$var wire 1 2 w_RX_DV $end

$scope module UART_RX_Inst $end
$var parameter 32 3 CLKS_PER_BIT $end
$var parameter 3 4 IDLE $end
$var parameter 3 5 RX_START_BIT $end
$var parameter 3 6 RX_DATA_BITS $end
$var parameter 3 7 RX_STOP_BIT $end
$var parameter 3 8 CLEANUP $end
$var wire 1 9 i_Clock $end
$var wire 1 ' i_RX_Serial $end
$var wire 1 2 o_RX_DV $end
$var wire 1 * o_RX_Byte [7] $end
$var wire 1 + o_RX_Byte [6] $end
$var wire 1 , o_RX_Byte [5] $end
$var wire 1 - o_RX_Byte [4] $end
$var wire 1 . o_RX_Byte [3] $end
$var wire 1 / o_RX_Byte [2] $end
$var wire 1 0 o_RX_Byte [1] $end
$var wire 1 1 o_RX_Byte [0] $end
$var reg 8 : r_Clock_Count [7:0] $end
$var reg 3 ; r_Bit_Index [2:0] $end
$var reg 8 < r_RX_Byte [7:0] $end
$var reg 1 = r_RX_DV $end
$var reg 3 > r_SM_Main [2:0] $end
$upscope $end

$scope module UART_TX_Inst $end
$var parameter 32 ? CLKS_PER_BIT $end
$var parameter 2 @ IDLE $end
$var parameter 2 A TX_START_BIT $end
$var parameter 2 B TX_DATA_BITS $end
$var parameter 2 C TX_STOP_BIT $end
$var wire 1 D i_Rst_L $end
$var wire 1 E i_Clock $end
$var wire 1 F i_TX_DV $end
$var wire 1 G i_TX_Byte [7] $end
$var wire 1 H i_TX_Byte [6] $end
$var wire 1 I i_TX_Byte [5] $end
$var wire 1 J i_TX_Byte [4] $end
$var wire 1 K i_TX_Byte [3] $end
$var wire 1 L i_TX_Byte [2] $end
$var wire 1 M i_TX_Byte [1] $end
$var wire 1 N i_TX_Byte [0] $end
$var reg 1 O o_TX_Active $end
$var reg 1 P o_TX_Serial $end
$var reg 1 Q o_TX_Done $end
$var reg 3 R r_SM_Main [2:0] $end
$var reg 9 S r_Clock_Count [8:0] $end
$var reg 3 T r_Bit_Index [2:0] $end
$var reg 8 U r_TX_Data [7:0] $end
$upscope $end
$upscope $end
$enddefinitions $end
#0
$dumpvars
0$
0%
b0 )
b0 :
b0 ;
b0 <
0=
b0 >
xO
xP
xQ
bx R
bx S
bx T
bx U
b101000 !
b11011001 "
b10000110011000 #
b11011001 3
b0 4
b1 5
b10 6
b11 7
b100 8
b11011001 ?
b0 @
b1 A
b10 B
b11 C
x&
x'
x(
01
00
0/
0.
0-
0,
0+
0*
02
0N
0M
0L
0K
0J
0I
0H
0G
0F
0E
09
zD
$end
#2000
1$
19
1E
0Q
b0 R
#4000
0$
09
0E
#6000
1$
19
1E
1P
b0 S
b0 T
1%
b111111 )
1(
1F
1N
1M
1L
1K
1J
1I
1'
#8000
0$
09
0E
#10000
1$
19
1E
1O
b111111 U
b1 R
0%
1&
0F
#12000
0$
09
0E
#14000
1$
19
1E
0P
b1 S
0(
0'
#16000
0$
09
0E
#18000
1$
19
1E
b10 S
b1 >
#20000
0$
09
0E
#22000
1$
19
1E
b11 S
b1 :
#24000
0$
09
0E
#26000
1$
19
1E
b100 S
b10 :
#28000
0$
09
0E
#30000
1$
19
1E
b101 S
b11 :
#32000
0$
09
0E
#34000
1$
19
1E
b110 S
b100 :
#36000
0$
09
0E
#38000
1$
19
1E
b111 S
b101 :
#40000
0$
09
0E
#42000
1$
19
1E
b1000 S
b110 :
#44000
0$
09
0E
#46000
1$
19
1E
b1001 S
b111 :
#48000
0$
09
0E
#50000
1$
19
1E
b1010 S
b1000 :
#52000
0$
09
0E
#54000
1$
19
1E
b1011 S
b1001 :
#56000
0$
09
0E
#58000
1$
19
1E
b1100 S
b1010 :
#60000
0$
09
0E
#62000
1$
19
1E
b1101 S
b1011 :
#64000
0$
09
0E
#66000
1$
19
1E
b1110 S
b1100 :
#68000
0$
09
0E
#70000
1$
19
1E
b1111 S
b1101 :
#72000
0$
09
0E
#74000
1$
19
1E
b10000 S
b1110 :
#76000
0$
09
0E
#78000
1$
19
1E
b10001 S
b1111 :
#80000
0$
09
0E
#82000
1$
19
1E
b10010 S
b10000 :
#84000
0$
09
0E
#86000
1$
19
1E
b10011 S
b10001 :
#88000
0$
09
0E
#90000
1$
19
1E
b10100 S
b10010 :
#92000
0$
09
0E
#94000
1$
19
1E
b10101 S
b10011 :
#96000
0$
09
0E
#98000
1$
19
1E
b10110 S
b10100 :
#100000
0$
09
0E
#102000
1$
19
1E
b10111 S
b10101 :
#104000
0$
09
0E
#106000
1$
19
1E
b11000 S
b10110 :
#108000
0$
09
0E
#110000
1$
19
1E
b11001 S
b10111 :
#112000
0$
09
0E
#114000
1$
19
1E
b11010 S
b11000 :
#116000
0$
09
0E
#118000
1$
19
1E
b11011 S
b11001 :
#120000
0$
09
0E
#122000
1$
19
1E
b11100 S
b11010 :
#124000
0$
09
0E
#126000
1$
19
1E
b11101 S
b11011 :
#128000
0$
09
0E
#130000
1$
19
1E
b11110 S
b11100 :
#132000
0$
09
0E
#134000
1$
19
1E
b11111 S
b11101 :
#136000
0$
09
0E
#138000
1$
19
1E
b100000 S
b11110 :
#140000
0$
09
0E
#142000
1$
19
1E
b100001 S
b11111 :
#144000
0$
09
0E
#146000
1$
19
1E
b100010 S
b100000 :
#148000
0$
09
0E
#150000
1$
19
1E
b100011 S
b100001 :
#152000
0$
09
0E
#154000
1$
19
1E
b100100 S
b100010 :
#156000
0$
09
0E
#158000
1$
19
1E
b100101 S
b100011 :
#160000
0$
09
0E
#162000
1$
19
1E
b100110 S
b100100 :
#164000
0$
09
0E
#166000
1$
19
1E
b100111 S
b100101 :
#168000
0$
09
0E
#170000
1$
19
1E
b101000 S
b100110 :
#172000
0$
09
0E
#174000
1$
19
1E
b101001 S
b100111 :
#176000
0$
09
0E
#178000
1$
19
1E
b101010 S
b101000 :
#180000
0$
09
0E
#182000
1$
19
1E
b101011 S
b101001 :
#184000
0$
09
0E
#186000
1$
19
1E
b101100 S
b101010 :
#188000
0$
09
0E
#190000
1$
19
1E
b101101 S
b101011 :
#192000
0$
09
0E
#194000
1$
19
1E
b101110 S
b101100 :
#196000
0$
09
0E
#198000
1$
19
1E
b101111 S
b101101 :
#200000
0$
09
0E
#202000
1$
19
1E
b110000 S
b101110 :
#204000
0$
09
0E
#206000
1$
19
1E
b110001 S
b101111 :
#208000
0$
09
0E
#210000
1$
19
1E
b110010 S
b110000 :
#212000
0$
09
0E
#214000
1$
19
1E
b110011 S
b110001 :
#216000
0$
09
0E
#218000
1$
19
1E
b110100 S
b110010 :
#220000
0$
09
0E
#222000
1$
19
1E
b110101 S
b110011 :
#224000
0$
09
0E
#226000
1$
19
1E
b110110 S
b110100 :
#228000
0$
09
0E
#230000
1$
19
1E
b110111 S
b110101 :
#232000
0$
09
0E
#234000
1$
19
1E
b111000 S
b110110 :
#236000
0$
09
0E
#238000
1$
19
1E
b111001 S
b110111 :
#240000
0$
09
0E
#242000
1$
19
1E
b111010 S
b111000 :
#244000
0$
09
0E
#246000
1$
19
1E
b111011 S
b111001 :
#248000
0$
09
0E
#250000
1$
19
1E
b111100 S
b111010 :
#252000
0$
09
0E
#254000
1$
19
1E
b111101 S
b111011 :
#256000
0$
09
0E
#258000
1$
19
1E
b111110 S
b111100 :
#260000
0$
09
0E
#262000
1$
19
1E
b111111 S
b111101 :
#264000
0$
09
0E
#266000
1$
19
1E
b1000000 S
b111110 :
#268000
0$
09
0E
#270000
1$
19
1E
b1000001 S
b111111 :
#272000
0$
09
0E
#274000
1$
19
1E
b1000010 S
b1000000 :
#276000
0$
09
0E
#278000
1$
19
1E
b1000011 S
b1000001 :
#280000
0$
09
0E
#282000
1$
19
1E
b1000100 S
b1000010 :
#284000
0$
09
0E
#286000
1$
19
1E
b1000101 S
b1000011 :
#288000
0$
09
0E
#290000
1$
19
1E
b1000110 S
b1000100 :
#292000
0$
09
0E
#294000
1$
19
1E
b1000111 S
b1000101 :
#296000
0$
09
0E
#298000
1$
19
1E
b1001000 S
b1000110 :
#300000
0$
09
0E
#302000
1$
19
1E
b1001001 S
b1000111 :
#304000
0$
09
0E
#306000
1$
19
1E
b1001010 S
b1001000 :
#308000
0$
09
0E
#310000
1$
19
1E
b1001011 S
b1001001 :
#312000
0$
09
0E
#314000
1$
19
1E
b1001100 S
b1001010 :
#316000
0$
09
0E
#318000
1$
19
1E
b1001101 S
b1001011 :
#320000
0$
09
0E
#322000
1$
19
1E
b1001110 S
b1001100 :
#324000
0$
09
0E
#326000
1$
19
1E
b1001111 S
b1001101 :
#328000
0$
09
0E
#330000
1$
19
1E
b1010000 S
b1001110 :
#332000
0$
09
0E
#334000
1$
19
1E
b1010001 S
b1001111 :
#336000
0$
09
0E
#338000
1$
19
1E
b1010010 S
b1010000 :
#340000
0$
09
0E
#342000
1$
19
1E
b1010011 S
b1010001 :
#344000
0$
09
0E
#346000
1$
19
1E
b1010100 S
b1010010 :
#348000
0$
09
0E
#350000
1$
19
1E
b1010101 S
b1010011 :
#352000
0$
09
0E
#354000
1$
19
1E
b1010110 S
b1010100 :
#356000
0$
09
0E
#358000
1$
19
1E
b1010111 S
b1010101 :
#360000
0$
09
0E
#362000
1$
19
1E
b1011000 S
b1010110 :
#364000
0$
09
0E
#366000
1$
19
1E
b1011001 S
b1010111 :
#368000
0$
09
0E
#370000
1$
19
1E
b1011010 S
b1011000 :
#372000
0$
09
0E
#374000
1$
19
1E
b1011011 S
b1011001 :
#376000
0$
09
0E
#378000
1$
19
1E
b1011100 S
b1011010 :
#380000
0$
09
0E
#382000
1$
19
1E
b1011101 S
b1011011 :
#384000
0$
09
0E
#386000
1$
19
1E
b1011110 S
b1011100 :
#388000
0$
09
0E
#390000
1$
19
1E
b1011111 S
b1011101 :
#392000
0$
09
0E
#394000
1$
19
1E
b1100000 S
b1011110 :
#396000
0$
09
0E
#398000
1$
19
1E
b1100001 S
b1011111 :
#400000
0$
09
0E
#402000
1$
19
1E
b1100010 S
b1100000 :
#404000
0$
09
0E
#406000
1$
19
1E
b1100011 S
b1100001 :
#408000
0$
09
0E
#410000
1$
19
1E
b1100100 S
b1100010 :
#412000
0$
09
0E
#414000
1$
19
1E
b1100101 S
b1100011 :
#416000
0$
09
0E
#418000
1$
19
1E
b1100110 S
b1100100 :
#420000
0$
09
0E
#422000
1$
19
1E
b1100111 S
b1100101 :
#424000
0$
09
0E
#426000
1$
19
1E
b1101000 S
b1100110 :
#428000
0$
09
0E
#430000
1$
19
1E
b1101001 S
b1100111 :
#432000
0$
09
0E
#434000
1$
19
1E
b1101010 S
b1101000 :
#436000
0$
09
0E
#438000
1$
19
1E
b1101011 S
b1101001 :
#440000
0$
09
0E
#442000
1$
19
1E
b1101100 S
b1101010 :
#444000
0$
09
0E
#446000
1$
19
1E
b1101101 S
b1101011 :
#448000
0$
09
0E
#450000
1$
19
1E
b1101110 S
b1101100 :
#452000
0$
09
0E
#454000
1$
19
1E
b1101111 S
b0 :
b10 >
#456000
0$
09
0E
#458000
1$
19
1E
b1110000 S
b1 :
#460000
0$
09
0E
#462000
1$
19
1E
b1110001 S
b10 :
#464000
0$
09
0E
#466000
1$
19
1E
b1110010 S
b11 :
#468000
0$
09
0E
#470000
1$
19
1E
b1110011 S
b100 :
#472000
0$
09
0E
#474000
1$
19
1E
b1110100 S
b101 :
#476000
0$
09
0E
#478000
1$
19
1E
b1110101 S
b110 :
#480000
0$
09
0E
#482000
1$
19
1E
b1110110 S
b111 :
#484000
0$
09
0E
#486000
1$
19
1E
b1110111 S
b1000 :
#488000
0$
09
0E
#490000
1$
19
1E
b1111000 S
b1001 :
#492000
0$
09
0E
#494000
1$
19
1E
b1111001 S
b1010 :
#496000
0$
09
0E
#498000
1$
19
1E
b1111010 S
b1011 :
#500000
0$
09
0E
#502000
1$
19
1E
b1111011 S
b1100 :
#504000
0$
09
0E
#506000
1$
19
1E
b1111100 S
b1101 :
#508000
0$
09
0E
#510000
1$
19
1E
b1111101 S
b1110 :
#512000
0$
09
0E
#514000
1$
19
1E
b1111110 S
b1111 :
#516000
0$
09
0E
#518000
1$
19
1E
b1111111 S
b10000 :
#520000
0$
09
0E
#522000
1$
19
1E
b10000000 S
b10001 :
#524000
0$
09
0E
#526000
1$
19
1E
b10000001 S
b10010 :
#528000
0$
09
0E
#530000
1$
19
1E
b10000010 S
b10011 :
#532000
0$
09
0E
#534000
1$
19
1E
b10000011 S
b10100 :
#536000
0$
09
0E
#538000
1$
19
1E
b10000100 S
b10101 :
#540000
0$
09
0E
#542000
1$
19
1E
b10000101 S
b10110 :
#544000
0$
09
0E
#546000
1$
19
1E
b10000110 S
b10111 :
#548000
0$
09
0E
#550000
1$
19
1E
b10000111 S
b11000 :
#552000
0$
09
0E
#554000
1$
19
1E
b10001000 S
b11001 :
#556000
0$
09
0E
#558000
1$
19
1E
b10001001 S
b11010 :
#560000
0$
09
0E
#562000
1$
19
1E
b10001010 S
b11011 :
#564000
0$
09
0E
#566000
1$
19
1E
b10001011 S
b11100 :
#568000
0$
09
0E
#570000
1$
19
1E
b10001100 S
b11101 :
#572000
0$
09
0E
#574000
1$
19
1E
b10001101 S
b11110 :
#576000
0$
09
0E
#578000
1$
19
1E
b10001110 S
b11111 :
#580000
0$
09
0E
#582000
1$
19
1E
b10001111 S
b100000 :
#584000
0$
09
0E
#586000
1$
19
1E
b10010000 S
b100001 :
#588000
0$
09
0E
#590000
1$
19
1E
b10010001 S
b100010 :
#592000
0$
09
0E
#594000
1$
19
1E
b10010010 S
b100011 :
#596000
0$
09
0E
#598000
1$
19
1E
b10010011 S
b100100 :
#600000
0$
09
0E
#602000
1$
19
1E
b10010100 S
b100101 :
#604000
0$
09
0E
#606000
1$
19
1E
b10010101 S
b100110 :
#608000
0$
09
0E
#610000
1$
19
1E
b10010110 S
b100111 :
#612000
0$
09
0E
#614000
1$
19
1E
b10010111 S
b101000 :
#616000
0$
09
0E
#618000
1$
19
1E
b10011000 S
b101001 :
#620000
0$
09
0E
#622000
1$
19
1E
b10011001 S
b101010 :
#624000
0$
09
0E
#626000
1$
19
1E
b10011010 S
b101011 :
#628000
0$
09
0E
#630000
1$
19
1E
b10011011 S
b101100 :
#632000
0$
09
0E
#634000
1$
19
1E
b10011100 S
b101101 :
#636000
0$
09
0E
#638000
1$
19
1E
b10011101 S
b101110 :
#640000
0$
09
0E
#642000
1$
19
1E
b10011110 S
b101111 :
#644000
0$
09
0E
#646000
1$
19
1E
b10011111 S
b110000 :
#648000
0$
09
0E
#650000
1$
19
1E
b10100000 S
b110001 :
#652000
0$
09
0E
#654000
1$
19
1E
b10100001 S
b110010 :
#656000
0$
09
0E
#658000
1$
19
1E
b10100010 S
b110011 :
#660000
0$
09
0E
#662000
1$
19
1E
b10100011 S
b110100 :
#664000
0$
09
0E
#666000
1$
19
1E
b10100100 S
b110101 :
#668000
0$
09
0E
#670000
1$
19
1E
b10100101 S
b110110 :
#672000
0$
09
0E
#674000
1$
19
1E
b10100110 S
b110111 :
#676000
0$
09
0E
#678000
1$
19
1E
b10100111 S
b111000 :
#680000
0$
09
0E
#682000
1$
19
1E
b10101000 S
b111001 :
#684000
0$
09
0E
#686000
1$
19
1E
b10101001 S
b111010 :
#688000
0$
09
0E
#690000
1$
19
1E
b10101010 S
b111011 :
#692000
0$
09
0E
#694000
1$
19
1E
b10101011 S
b111100 :
#696000
0$
09
0E
#698000
1$
19
1E
b10101100 S
b111101 :
#700000
0$
09
0E
#702000
1$
19
1E
b10101101 S
b111110 :
#704000
0$
09
0E
#706000
1$
19
1E
b10101110 S
b111111 :
#708000
0$
09
0E
#710000
1$
19
1E
b10101111 S
b1000000 :
#712000
0$
09
0E
#714000
1$
19
1E
b10110000 S
b1000001 :
#716000
0$
09
0E
#718000
1$
19
1E
b10110001 S
b1000010 :
#720000
0$
09
0E
#722000
1$
19
1E
b10110010 S
b1000011 :
#724000
0$
09
0E
#726000
1$
19
1E
b10110011 S
b1000100 :
#728000
0$
09
0E
#730000
1$
19
1E
b10110100 S
b1000101 :
#732000
0$
09
0E
#734000
1$
19
1E
b10110101 S
b1000110 :
#736000
0$
09
0E
#738000
1$
19
1E
b10110110 S
b1000111 :
#740000
0$
09
0E
#742000
1$
19
1E
b10110111 S
b1001000 :
#744000
0$
09
0E
#746000
1$
19
1E
b10111000 S
b1001001 :
#748000
0$
09
0E
#750000
1$
19
1E
b10111001 S
b1001010 :
#752000
0$
09
0E
#754000
1$
19
1E
b10111010 S
b1001011 :
#756000
0$
09
0E
#758000
1$
19
1E
b10111011 S
b1001100 :
#760000
0$
09
0E
#762000
1$
19
1E
b10111100 S
b1001101 :
#764000
0$
09
0E
#766000
1$
19
1E
b10111101 S
b1001110 :
#768000
0$
09
0E
#770000
1$
19
1E
b10111110 S
b1001111 :
#772000
0$
09
0E
#774000
1$
19
1E
b10111111 S
b1010000 :
#776000
0$
09
0E
#778000
1$
19
1E
b11000000 S
b1010001 :
#780000
0$
09
0E
#782000
1$
19
1E
b11000001 S
b1010010 :
#784000
0$
09
0E
#786000
1$
19
1E
b11000010 S
b1010011 :
#788000
0$
09
0E
#790000
1$
19
1E
b11000011 S
b1010100 :
#792000
0$
09
0E
#794000
1$
19
1E
b11000100 S
b1010101 :
#796000
0$
09
0E
#798000
1$
19
1E
b11000101 S
b1010110 :
#800000
0$
09
0E
#802000
1$
19
1E
b11000110 S
b1010111 :
#804000
0$
09
0E
#806000
1$
19
1E
b11000111 S
b1011000 :
#808000
0$
09
0E
#810000
1$
19
1E
b11001000 S
b1011001 :
#812000
0$
09
0E
#814000
1$
19
1E
b11001001 S
b1011010 :
#816000
0$
09
0E
#818000
1$
19
1E
b11001010 S
b1011011 :
#820000
0$
09
0E
#822000
1$
19
1E
b11001011 S
b1011100 :
#824000
0$
09
0E
#826000
1$
19
1E
b11001100 S
b1011101 :
#828000
0$
09
0E
#830000
1$
19
1E
b11001101 S
b1011110 :
#832000
0$
09
0E
#834000
1$
19
1E
b11001110 S
b1011111 :
#836000
0$
09
0E
#838000
1$
19
1E
b11001111 S
b1100000 :
#840000
0$
09
0E
#842000
1$
19
1E
b11010000 S
b1100001 :
#844000
0$
09
0E
#846000
1$
19
1E
b11010001 S
b1100010 :
#848000
0$
09
0E
#850000
1$
19
1E
b11010010 S
b1100011 :
#852000
0$
09
0E
#854000
1$
19
1E
b11010011 S
b1100100 :
#856000
0$
09
0E
#858000
1$
19
1E
b11010100 S
b1100101 :
#860000
0$
09
0E
#862000
1$
19
1E
b11010101 S
b1100110 :
#864000
0$
09
0E
#866000
1$
19
1E
b11010110 S
b1100111 :
#868000
0$
09
0E
#870000
1$
19
1E
b11010111 S
b1101000 :
#872000
0$
09
0E
#874000
1$
19
1E
b11011000 S
b1101001 :
#876000
0$
09
0E
#878000
1$
19
1E
b0 S
b10 R
b1101010 :
#880000
0$
09
0E
#882000
1$
19
1E
1P
b1 S
b1101011 :
1(
1'
#884000
0$
09
0E
#886000
1$
19
1E
b10 S
b1101100 :
#888000
0$
09
0E
#890000
1$
19
1E
b11 S
b1101101 :
#892000
0$
09
0E
#894000
1$
19
1E
b100 S
b1101110 :
#896000
0$
09
0E
#898000
1$
19
1E
b101 S
b1101111 :
#900000
0$
09
0E
#902000
1$
19
1E
b110 S
b1110000 :
#904000
0$
09
0E
#906000
1$
19
1E
b111 S
b1110001 :
#908000
0$
09
0E
#910000
1$
19
1E
b1000 S
b1110010 :
#912000
0$
09
0E
#914000
1$
19
1E
b1001 S
b1110011 :
#916000
0$
09
0E
#918000
1$
19
1E
b1010 S
b1110100 :
#920000
0$
09
0E
#922000
1$
19
1E
b1011 S
b1110101 :
#924000
0$
09
0E
#926000
1$
19
1E
b1100 S
b1110110 :
#928000
0$
09
0E
#930000
1$
19
1E
b1101 S
b1110111 :
#932000
0$
09
0E
#934000
1$
19
1E
b1110 S
b1111000 :
#936000
0$
09
0E
#938000
1$
19
1E
b1111 S
b1111001 :
#940000
0$
09
0E
#942000
1$
19
1E
b10000 S
b1111010 :
#944000
0$
09
0E
#946000
1$
19
1E
b10001 S
b1111011 :
#948000
0$
09
0E
#950000
1$
19
1E
b10010 S
b1111100 :
#952000
0$
09
0E
#954000
1$
19
1E
b10011 S
b1111101 :
